wsocks/__init__.py
wsocks/run_client.py
wsocks/run_server.py
wsocks/client/__init__.py
wsocks/client/socks5_server.py
wsocks/client/ws_adapter.py
wsocks/client/ws_adapter_new.py
wsocks/client/ws_adapter_threaded.py
wsocks/client/ws_client.py
wsocks/common/__init__.py
wsocks/common/crypto.py
wsocks/common/event_loop.py
wsocks/common/logger.py
wsocks/common/protocol.py
wsocks/server/__init__.py
wsocks/server/tcp_client.py
wsocks/server/ws_handler.py
wsocks-1.0.4.dist-info/METADATA
wsocks-1.0.4.dist-info/WHEEL
wsocks-1.0.4.dist-info/entry_points.txt
wsocks-1.0.4.dist-info/top_level.txt
wsocks-1.0.4.dist-info/RECORD
