Metadata-Version: 2.1
Name: wsocks
Version: 1.0.4
Summary: UNKNOWN
Home-page: https://github.com/sazima/WSocks
License: UNKNOWN
Platform: UNKNOWN
Requires-Python: >=3.6
Requires-Dist: tornado
Requires-Dist: websockets
Requires-Dist: xxhash (>=3.0.0)
Requires-Dist: msgpack
Requires-Dist: uvloop ; sys_platform != "win32"
Provides-Extra: no-uvloop
